MANIFEST.in
README.txt
setup.py
django_framework/__init__.py
django_framework.egg-info/PKG-INFO
django_framework.egg-info/SOURCES.txt
django_framework.egg-info/dependency_links.txt
django_framework.egg-info/requires.txt
django_framework.egg-info/top_level.txt
django_framework/base_framework/__init__.py
django_framework/base_framework/routes.py
django_framework/base_framework/urls.py
django_framework/base_framework/admin_api/__init__.py
django_framework/base_framework/admin_api/urls.py
django_framework/base_framework/admin_api/clear_cache/__init__.py
django_framework/base_framework/admin_api/clear_cache/api.py
django_framework/base_framework/admin_api/clear_cache/urls.py
django_framework/base_framework/admin_api/is_alive_api/__init__.py
django_framework/base_framework/admin_api/is_alive_api/api.py
django_framework/base_framework/admin_api/is_alive_api/urls.py
django_framework/base_framework/admin_api/profile_delete_api/__init__.py
django_framework/base_framework/admin_api/profile_delete_api/api.py
django_framework/base_framework/admin_api/profile_delete_api/urls.py
django_framework/base_framework/model_api/__init__.py
django_framework/base_framework/model_api/api.py
django_framework/base_framework/model_api/routes.py
django_framework/base_framework/model_api/urls.py
django_framework/base_framework/model_api/widget/__init__.py
django_framework/base_framework/model_api/widget/model_api.py
django_framework/base_framework/model_jobs_api/__init__.py
django_framework/base_framework/model_jobs_api/api.py
django_framework/base_framework/model_jobs_api/routes.py
django_framework/base_framework/model_jobs_api/urls.py
django_framework/base_framework/model_jobs_api/widget/__init__.py
django_framework/base_framework/model_jobs_api/widget/model_job_api.py
django_framework/base_framework/server_docs_api/__init__.py
django_framework/base_framework/server_docs_api/api.py
django_framework/base_framework/server_docs_api/urls.py
django_framework/base_framework/server_docs_api/model_docs/__init__.py
django_framework/base_framework/server_docs_api/model_docs/api.py
django_framework/base_framework/server_docs_api/model_docs/widgets/__init__.py
