Metadata-Version: 1.0
Name: django-framework
Version: 0.1.87
Summary: Useful stuff for django.  .
Home-page: http://pypi.python.org/pypi/MyApplication_v010/
Author: redsands
Author-email: name@addr.ess
License: UNKNOWN
Platform: UNKNOWN
